LibreAssist/__init__.py
LibreAssist/inference/__init__.py
LibreAssist/inference/_setting.py
LibreAssist/inference/inference.py
LibreAssist/user_interface/__init__.py
LibreAssist/user_interface/_info.py
LibreAssist/user_interface/gardio_interface.py
LibreAssist/user_interface/theme.py
LibreAssist-0.0.1.dist-info/LICENSE
LibreAssist-0.0.1.dist-info/METADATA
LibreAssist-0.0.1.dist-info/WHEEL
LibreAssist-0.0.1.dist-info/top_level.txt
LibreAssist-0.0.1.dist-info/RECORD
