Metadata-Version: 2.1
Name: LibreAssist
Version: 0.0.1
Summary: An open-source library LibreAssist is a Local Assistance here to help you with your needs on your personal computer
Home-page: https://github.com/erfanzar/LibreAssist
Author: Erfan Zare Chavoshi
Author-email: erfanzare82@eyahoo.com
Keywords: machine learning,deep learning,ggml,gguf,c++
Classifier: Development Status :: 3 - Alpha
Classifier: Intended Audience :: Developers
Classifier: Topic :: Scientific/Engineering :: Artificial Intelligence
Classifier: License :: OSI Approved :: Apache Software License
Classifier: Programming Language :: Python :: 3
Classifier: Programming Language :: Python :: 3.8
Classifier: Programming Language :: Python :: 3.9
Classifier: Programming Language :: Python :: 3.10
Classifier: Programming Language :: Python :: 3.11
Classifier: Programming Language :: Python :: 3.12
Requires-Python: >=3.8
License-File: LICENSE
Requires-Dist: absl-py ==2.0.0
Requires-Dist: diskcache ~=5.6.3
Requires-Dist: gradio ==4.10.0
Requires-Dist: llama-cpp-python ==0.2.25
Requires-Dist: numpy ~=1.26.1
Requires-Dist: pydantic-core ==2.14.6
Requires-Dist: typing ~=3.7.4.3
